wise_decision_engine/__init__.py
wise_decision_engine/adapters.py
wise_decision_engine/cache.py
wise_decision_engine/core.py
wise_decision_engine/schema_inference.py
wise_decision_engine/session_cache.py
wise_decision_engine/spark_utils.py
wise_decision_engine-0.6.0.dist-info/METADATA
wise_decision_engine-0.6.0.dist-info/WHEEL
wise_decision_engine-0.6.0.dist-info/licenses/LICENSE
wise_decision_engine-0.6.0.dist-info/RECORD
