Metadata-Version: 2.4
Name: wise-decision-engine
Version: 0.6.0
Summary: Uma abstração moderna e inteligente para zen-engine com otimizações avançadas para Spark/Databricks
License: MIT
License-File: LICENSE
Keywords: zen-engine,databricks,spark,decision-engine,schema-inference
Author: Five Acts
Author-email: dev@five-acts.com
Requires-Python: >=3.8,<4.0
Classifier: Development Status :: 3 - Alpha
Classifier: Intended Audience :: Developers
Classifier: License :: OSI Approved :: MIT License
Classifier: Operating System :: OS Independent
Classifier: Programming Language :: Python :: 3
Classifier: Programming Language :: Python :: 3.8
Classifier: Programming Language :: Python :: 3.9
Classifier: Programming Language :: Python :: 3.10
Classifier: Programming Language :: Python :: 3.11
Classifier: Programming Language :: Python :: 3.12
Classifier: Programming Language :: Python :: 3.13
Classifier: Programming Language :: Python :: 3.14
Classifier: Topic :: Database
Classifier: Topic :: Scientific/Engineering :: Information Analysis
Classifier: Topic :: Software Development :: Libraries :: Python Modules
Provides-Extra: all
Provides-Extra: databricks
Provides-Extra: dev-local
Provides-Extra: spark
Requires-Dist: zen-engine (>=0.50.0,<0.51.0)
Project-URL: Documentation, https://github.com/five-acts/wise-decision-engine/wiki
Project-URL: Homepage, https://github.com/five-acts/wise-decision-engine
Project-URL: Repository, https://github.com/five-acts/wise-decision-engine
